{
  "id": "fdf7aa96-5689-4603-bd8a-3737327f08b3",
  "prevId": "407766bf-d4c7-4a82-83d9-888264d47951",
  "version": "7",
  "dialect": "postgresql",
  "tables": {
    "public.account": {
      "name": "account",
      "schema": "",
      "columns": {
        "id": {
          "name": "id",
          "type": "text",
          "primaryKey": true,
          "notNull": true
        },
        "account_id": {
          "name": "account_id",
          "type": "text",
          "primaryKey": false,
          "notNull": true
        },
        "provider_id": {
          "name": "provider_id",
          "type": "text",
          "primaryKey": false,
          "notNull": true
        },
        "user_id": {
          "name": "user_id",
          "type": "text",
          "primaryKey": false,
          "notNull": true
        },
        "access_token": {
          "name": "access_token",
          "type": "text",
          "primaryKey": false,
          "notNull": false
        },
        "refresh_token": {
          "name": "refresh_token",
          "type": "text",
          "primaryKey": false,
          "notNull": false
        },
        "id_token": {
          "name": "id_token",
          "type": "text",
          "primaryKey": false,
          "notNull": false
        },
        "access_token_expires_at": {
          "name": "access_token_expires_at",
          "type": "timestamp",
          "primaryKey": false,
          "notNull": false
        },
        "refresh_token_expires_at": {
          "name": "refresh_token_expires_at",
          "type": "timestamp",
          "primaryKey": false,
          "notNull": false
        },
        "scope": {
          "name": "scope",
          "type": "text",
          "primaryKey": false,
          "notNull": false
        },
        "password": {
          "name": "password",
          "type": "text",
          "primaryKey": false,
          "notNull": false
        },
        "created_at": {
          "name": "created_at",
          "type": "timestamp",
          "primaryKey": false,
          "notNull": true,
          "default": "now()"
        },
        "updated_at": {
          "name": "updated_at",
          "type": "timestamp",
          "primaryKey": false,
          "notNull": true
        }
      },
      "indexes": {},
      "foreignKeys": {
        "account_user_id_user_id_fk": {
          "name": "account_user_id_user_id_fk",
          "tableFrom": "account",
          "tableTo": "user",
          "columnsFrom": [
            "user_id"
          ],
          "columnsTo": [
            "id"
          ],
          "onDelete": "cascade",
          "onUpdate": "no action"
        }
      },
      "compositePrimaryKeys": {},
      "uniqueConstraints": {},
      "policies": {},
      "checkConstraints": {},
      "isRLSEnabled": false
    },
    "public.session": {
      "name": "session",
      "schema": "",
      "columns": {
        "id": {
          "name": "id",
          "type": "text",
          "primaryKey": true,
          "notNull": true
        },
        "expires_at": {
          "name": "expires_at",
          "type": "timestamp",
          "primaryKey": false,
          "notNull": true
        },
        "token": {
          "name": "token",
          "type": "text",
          "primaryKey": false,
          "notNull": true
        },
        "created_at": {
          "name": "created_at",
          "type": "timestamp",
          "primaryKey": false,
          "notNull": true,
          "default": "now()"
        },
        "updated_at": {
          "name": "updated_at",
          "type": "timestamp",
          "primaryKey": false,
          "notNull": true
        },
        "ip_address": {
          "name": "ip_address",
          "type": "text",
          "primaryKey": false,
          "notNull": false
        },
        "user_agent": {
          "name": "user_agent",
          "type": "text",
          "primaryKey": false,
          "notNull": false
        },
        "user_id": {
          "name": "user_id",
          "type": "text",
          "primaryKey": false,
          "notNull": true
        }
      },
      "indexes": {},
      "foreignKeys": {
        "session_user_id_user_id_fk": {
          "name": "session_user_id_user_id_fk",
          "tableFrom": "session",
          "tableTo": "user",
          "columnsFrom": [
            "user_id"
          ],
          "columnsTo": [
            "id"
          ],
          "onDelete": "cascade",
          "onUpdate": "no action"
        }
      },
      "compositePrimaryKeys": {},
      "uniqueConstraints": {
        "session_token_unique": {
          "name": "session_token_unique",
          "nullsNotDistinct": false,
          "columns": [
            "token"
          ]
        }
      },
      "policies": {},
      "checkConstraints": {},
      "isRLSEnabled": false
    },
    "public.user": {
      "name": "user",
      "schema": "",
      "columns": {
        "id": {
          "name": "id",
          "type": "text",
          "primaryKey": true,
          "notNull": true
        },
        "name": {
          "name": "name",
          "type": "text",
          "primaryKey": false,
          "notNull": true
        },
        "email": {
          "name": "email",
          "type": "text",
          "primaryKey": false,
          "notNull": true
        },
        "email_verified": {
          "name": "email_verified",
          "type": "boolean",
          "primaryKey": false,
          "notNull": true,
          "default": false
        },
        "image": {
          "name": "image",
          "type": "text",
          "primaryKey": false,
          "notNull": false
        },
        "created_at": {
          "name": "created_at",
          "type": "timestamp",
          "primaryKey": false,
          "notNull": true,
          "default": "now()"
        },
        "updated_at": {
          "name": "updated_at",
          "type": "timestamp",
          "primaryKey": false,
          "notNull": true,
          "default": "now()"
        }
      },
      "indexes": {},
      "foreignKeys": {},
      "compositePrimaryKeys": {},
      "uniqueConstraints": {
        "user_email_unique": {
          "name": "user_email_unique",
          "nullsNotDistinct": false,
          "columns": [
            "email"
          ]
        }
      },
      "policies": {},
      "checkConstraints": {},
      "isRLSEnabled": false
    },
    "public.verification": {
      "name": "verification",
      "schema": "",
      "columns": {
        "id": {
          "name": "id",
          "type": "text",
          "primaryKey": true,
          "notNull": true
        },
        "identifier": {
          "name": "identifier",
          "type": "text",
          "primaryKey": false,
          "notNull": true
        },
        "value": {
          "name": "value",
          "type": "text",
          "primaryKey": false,
          "notNull": true
        },
        "expires_at": {
          "name": "expires_at",
          "type": "timestamp",
          "primaryKey": false,
          "notNull": true
        },
        "created_at": {
          "name": "created_at",
          "type": "timestamp",
          "primaryKey": false,
          "notNull": true,
          "default": "now()"
        },
        "updated_at": {
          "name": "updated_at",
          "type": "timestamp",
          "primaryKey": false,
          "notNull": true,
          "default": "now()"
        }
      },
      "indexes": {},
      "foreignKeys": {},
      "compositePrimaryKeys": {},
      "uniqueConstraints": {},
      "policies": {},
      "checkConstraints": {},
      "isRLSEnabled": false
    },
    "public.chat_messages": {
      "name": "chat_messages",
      "schema": "",
      "columns": {
        "id": {
          "name": "id",
          "type": "uuid",
          "primaryKey": true,
          "notNull": true,
          "default": "gen_random_uuid()"
        },
        "user_id": {
          "name": "user_id",
          "type": "text",
          "primaryKey": false,
          "notNull": true
        },
        "role": {
          "name": "role",
          "type": "chat_role",
          "typeSchema": "public",
          "primaryKey": false,
          "notNull": true
        },
        "content": {
          "name": "content",
          "type": "text",
          "primaryKey": false,
          "notNull": true
        },
        "created_at": {
          "name": "created_at",
          "type": "timestamp with time zone",
          "primaryKey": false,
          "notNull": true,
          "default": "now()"
        }
      },
      "indexes": {},
      "foreignKeys": {
        "chat_messages_user_id_user_id_fk": {
          "name": "chat_messages_user_id_user_id_fk",
          "tableFrom": "chat_messages",
          "tableTo": "user",
          "columnsFrom": [
            "user_id"
          ],
          "columnsTo": [
            "id"
          ],
          "onDelete": "cascade",
          "onUpdate": "no action"
        }
      },
      "compositePrimaryKeys": {},
      "uniqueConstraints": {},
      "policies": {},
      "checkConstraints": {},
      "isRLSEnabled": false
    },
    "public.dates": {
      "name": "dates",
      "schema": "",
      "columns": {
        "id": {
          "name": "id",
          "type": "uuid",
          "primaryKey": true,
          "notNull": true,
          "default": "gen_random_uuid()"
        },
        "user_id": {
          "name": "user_id",
          "type": "text",
          "primaryKey": false,
          "notNull": true
        },
        "person_id": {
          "name": "person_id",
          "type": "uuid",
          "primaryKey": false,
          "notNull": true
        },
        "title": {
          "name": "title",
          "type": "text",
          "primaryKey": false,
          "notNull": true
        },
        "location": {
          "name": "location",
          "type": "text",
          "primaryKey": false,
          "notNull": false
        },
        "date_time": {
          "name": "date_time",
          "type": "text",
          "primaryKey": false,
          "notNull": false
        },
        "budget": {
          "name": "budget",
          "type": "text",
          "primaryKey": false,
          "notNull": false
        },
        "status": {
          "name": "status",
          "type": "date_status",
          "typeSchema": "public",
          "primaryKey": false,
          "notNull": true,
          "default": "'planned'"
        },
        "reminder_3_days": {
          "name": "reminder_3_days",
          "type": "boolean",
          "primaryKey": false,
          "notNull": true,
          "default": false
        },
        "reminder_1_day": {
          "name": "reminder_1_day",
          "type": "boolean",
          "primaryKey": false,
          "notNull": true,
          "default": false
        },
        "reminder_1_hour": {
          "name": "reminder_1_hour",
          "type": "boolean",
          "primaryKey": false,
          "notNull": true,
          "default": false
        },
        "notes": {
          "name": "notes",
          "type": "text",
          "primaryKey": false,
          "notNull": false
        },
        "rating": {
          "name": "rating",
          "type": "integer",
          "primaryKey": false,
          "notNull": false
        },
        "went_well": {
          "name": "went_well",
          "type": "text",
          "primaryKey": false,
          "notNull": false
        },
        "went_poorly": {
          "name": "went_poorly",
          "type": "text",
          "primaryKey": false,
          "notNull": false
        },
        "want_another_date": {
          "name": "want_another_date",
          "type": "boolean",
          "primaryKey": false,
          "notNull": false
        },
        "created_at": {
          "name": "created_at",
          "type": "timestamp with time zone",
          "primaryKey": false,
          "notNull": true,
          "default": "now()"
        }
      },
      "indexes": {},
      "foreignKeys": {
        "dates_user_id_user_id_fk": {
          "name": "dates_user_id_user_id_fk",
          "tableFrom": "dates",
          "tableTo": "user",
          "columnsFrom": [
            "user_id"
          ],
          "columnsTo": [
            "id"
          ],
          "onDelete": "cascade",
          "onUpdate": "no action"
        },
        "dates_person_id_persons_id_fk": {
          "name": "dates_person_id_persons_id_fk",
          "tableFrom": "dates",
          "tableTo": "persons",
          "columnsFrom": [
            "person_id"
          ],
          "columnsTo": [
            "id"
          ],
          "onDelete": "cascade",
          "onUpdate": "no action"
        }
      },
      "compositePrimaryKeys": {},
      "uniqueConstraints": {},
      "policies": {},
      "checkConstraints": {},
      "isRLSEnabled": false
    },
    "public.interactions": {
      "name": "interactions",
      "schema": "",
      "columns": {
        "id": {
          "name": "id",
          "type": "uuid",
          "primaryKey": true,
          "notNull": true,
          "default": "gen_random_uuid()"
        },
        "user_id": {
          "name": "user_id",
          "type": "text",
          "primaryKey": false,
          "notNull": true
        },
        "person_id": {
          "name": "person_id",
          "type": "uuid",
          "primaryKey": false,
          "notNull": true
        },
        "type": {
          "name": "type",
          "type": "interaction_type",
          "typeSchema": "public",
          "primaryKey": false,
          "notNull": true
        },
        "title": {
          "name": "title",
          "type": "text",
          "primaryKey": false,
          "notNull": true
        },
        "notes": {
          "name": "notes",
          "type": "text",
          "primaryKey": false,
          "notNull": false
        },
        "occurred_at": {
          "name": "occurred_at",
          "type": "timestamp with time zone",
          "primaryKey": false,
          "notNull": true
        },
        "created_at": {
          "name": "created_at",
          "type": "timestamp with time zone",
          "primaryKey": false,
          "notNull": true,
          "default": "now()"
        }
      },
      "indexes": {},
      "foreignKeys": {
        "interactions_user_id_user_id_fk": {
          "name": "interactions_user_id_user_id_fk",
          "tableFrom": "interactions",
          "tableTo": "user",
          "columnsFrom": [
            "user_id"
          ],
          "columnsTo": [
            "id"
          ],
          "onDelete": "cascade",
          "onUpdate": "no action"
        },
        "interactions_person_id_persons_id_fk": {
          "name": "interactions_person_id_persons_id_fk",
          "tableFrom": "interactions",
          "tableTo": "persons",
          "columnsFrom": [
            "person_id"
          ],
          "columnsTo": [
            "id"
          ],
          "onDelete": "cascade",
          "onUpdate": "no action"
        }
      },
      "compositePrimaryKeys": {},
      "uniqueConstraints": {},
      "policies": {},
      "checkConstraints": {},
      "isRLSEnabled": false
    },
    "public.notes": {
      "name": "notes",
      "schema": "",
      "columns": {
        "id": {
          "name": "id",
          "type": "uuid",
          "primaryKey": true,
          "notNull": true,
          "default": "gen_random_uuid()"
        },
        "user_id": {
          "name": "user_id",
          "type": "text",
          "primaryKey": false,
          "notNull": true
        },
        "person_id": {
          "name": "person_id",
          "type": "uuid",
          "primaryKey": false,
          "notNull": true
        },
        "content": {
          "name": "content",
          "type": "text",
          "primaryKey": false,
          "notNull": true
        },
        "created_at": {
          "name": "created_at",
          "type": "timestamp with time zone",
          "primaryKey": false,
          "notNull": true,
          "default": "now()"
        }
      },
      "indexes": {},
      "foreignKeys": {
        "notes_user_id_user_id_fk": {
          "name": "notes_user_id_user_id_fk",
          "tableFrom": "notes",
          "tableTo": "user",
          "columnsFrom": [
            "user_id"
          ],
          "columnsTo": [
            "id"
          ],
          "onDelete": "cascade",
          "onUpdate": "no action"
        },
        "notes_person_id_persons_id_fk": {
          "name": "notes_person_id_persons_id_fk",
          "tableFrom": "notes",
          "tableTo": "persons",
          "columnsFrom": [
            "person_id"
          ],
          "columnsTo": [
            "id"
          ],
          "onDelete": "cascade",
          "onUpdate": "no action"
        }
      },
      "compositePrimaryKeys": {},
      "uniqueConstraints": {},
      "policies": {},
      "checkConstraints": {},
      "isRLSEnabled": false
    },
    "public.persons": {
      "name": "persons",
      "schema": "",
      "columns": {
        "id": {
          "name": "id",
          "type": "uuid",
          "primaryKey": true,
          "notNull": true,
          "default": "gen_random_uuid()"
        },
        "user_id": {
          "name": "user_id",
          "type": "text",
          "primaryKey": false,
          "notNull": true
        },
        "name": {
          "name": "name",
          "type": "text",
          "primaryKey": false,
          "notNull": true
        },
        "location": {
          "name": "location",
          "type": "text",
          "primaryKey": false,
          "notNull": true
        },
        "photo_url": {
          "name": "photo_url",
          "type": "text",
          "primaryKey": false,
          "notNull": false
        },
        "age": {
          "name": "age",
          "type": "integer",
          "primaryKey": false,
          "notNull": false
        },
        "birthday": {
          "name": "birthday",
          "type": "text",
          "primaryKey": false,
          "notNull": false
        },
        "zodiac": {
          "name": "zodiac",
          "type": "zodiac",
          "typeSchema": "public",
          "primaryKey": false,
          "notNull": false
        },
        "phone_number": {
          "name": "phone_number",
          "type": "text",
          "primaryKey": false,
          "notNull": false
        },
        "instagram": {
          "name": "instagram",
          "type": "text",
          "primaryKey": false,
          "notNull": false
        },
        "tiktok": {
          "name": "tiktok",
          "type": "text",
          "primaryKey": false,
          "notNull": false
        },
        "twitter_x": {
          "name": "twitter_x",
          "type": "text",
          "primaryKey": false,
          "notNull": false
        },
        "facebook": {
          "name": "facebook",
          "type": "text",
          "primaryKey": false,
          "notNull": false
        },
        "interest_level": {
          "name": "interest_level",
          "type": "integer",
          "primaryKey": false,
          "notNull": false
        },
        "attractiveness": {
          "name": "attractiveness",
          "type": "integer",
          "primaryKey": false,
          "notNull": false
        },
        "sexual_chemistry": {
          "name": "sexual_chemistry",
          "type": "integer",
          "primaryKey": false,
          "notNull": false
        },
        "communication": {
          "name": "communication",
          "type": "integer",
          "primaryKey": false,
          "notNull": false
        },
        "overall_chemistry": {
          "name": "overall_chemistry",
          "type": "integer",
          "primaryKey": false,
          "notNull": false
        },
        "consistency": {
          "name": "consistency",
          "type": "integer",
          "primaryKey": false,
          "notNull": false
        },
        "emotional_availability": {
          "name": "emotional_availability",
          "type": "integer",
          "primaryKey": false,
          "notNull": false
        },
        "date_planning": {
          "name": "date_planning",
          "type": "integer",
          "primaryKey": false,
          "notNull": false
        },
        "alignment": {
          "name": "alignment",
          "type": "integer",
          "primaryKey": false,
          "notNull": false
        },
        "connection_type": {
          "name": "connection_type",
          "type": "connection_type",
          "typeSchema": "public",
          "primaryKey": false,
          "notNull": false
        },
        "connection_type_custom": {
          "name": "connection_type_custom",
          "type": "text",
          "primaryKey": false,
          "notNull": false
        },
        "favorite_foods": {
          "name": "favorite_foods",
          "type": "text[]",
          "primaryKey": false,
          "notNull": false
        },
        "hobbies": {
          "name": "hobbies",
          "type": "text[]",
          "primaryKey": false,
          "notNull": false
        },
        "red_flags": {
          "name": "red_flags",
          "type": "text[]",
          "primaryKey": false,
          "notNull": false
        },
        "green_flags": {
          "name": "green_flags",
          "type": "text[]",
          "primaryKey": false,
          "notNull": false
        },
        "is_benched": {
          "name": "is_benched",
          "type": "boolean",
          "primaryKey": false,
          "notNull": true,
          "default": false
        },
        "bench_reason": {
          "name": "bench_reason",
          "type": "text",
          "primaryKey": false,
          "notNull": false
        },
        "created_at": {
          "name": "created_at",
          "type": "timestamp with time zone",
          "primaryKey": false,
          "notNull": true,
          "default": "now()"
        },
        "updated_at": {
          "name": "updated_at",
          "type": "timestamp with time zone",
          "primaryKey": false,
          "notNull": true,
          "default": "now()"
        }
      },
      "indexes": {},
      "foreignKeys": {
        "persons_user_id_user_id_fk": {
          "name": "persons_user_id_user_id_fk",
          "tableFrom": "persons",
          "tableTo": "user",
          "columnsFrom": [
            "user_id"
          ],
          "columnsTo": [
            "id"
          ],
          "onDelete": "cascade",
          "onUpdate": "no action"
        }
      },
      "compositePrimaryKeys": {},
      "uniqueConstraints": {},
      "policies": {},
      "checkConstraints": {},
      "isRLSEnabled": false
    },
    "public.reminders": {
      "name": "reminders",
      "schema": "",
      "columns": {
        "id": {
          "name": "id",
          "type": "uuid",
          "primaryKey": true,
          "notNull": true,
          "default": "gen_random_uuid()"
        },
        "user_id": {
          "name": "user_id",
          "type": "text",
          "primaryKey": false,
          "notNull": true
        },
        "person_id": {
          "name": "person_id",
          "type": "uuid",
          "primaryKey": false,
          "notNull": true
        },
        "text": {
          "name": "text",
          "type": "text",
          "primaryKey": false,
          "notNull": true
        },
        "remind_at": {
          "name": "remind_at",
          "type": "timestamp with time zone",
          "primaryKey": false,
          "notNull": true
        },
        "created_at": {
          "name": "created_at",
          "type": "timestamp with time zone",
          "primaryKey": false,
          "notNull": true,
          "default": "now()"
        }
      },
      "indexes": {},
      "foreignKeys": {
        "reminders_user_id_user_id_fk": {
          "name": "reminders_user_id_user_id_fk",
          "tableFrom": "reminders",
          "tableTo": "user",
          "columnsFrom": [
            "user_id"
          ],
          "columnsTo": [
            "id"
          ],
          "onDelete": "cascade",
          "onUpdate": "no action"
        },
        "reminders_person_id_persons_id_fk": {
          "name": "reminders_person_id_persons_id_fk",
          "tableFrom": "reminders",
          "tableTo": "persons",
          "columnsFrom": [
            "person_id"
          ],
          "columnsTo": [
            "id"
          ],
          "onDelete": "cascade",
          "onUpdate": "no action"
        }
      },
      "compositePrimaryKeys": {},
      "uniqueConstraints": {},
      "policies": {},
      "checkConstraints": {},
      "isRLSEnabled": false
    },
    "public.safety_checkins": {
      "name": "safety_checkins",
      "schema": "",
      "columns": {
        "id": {
          "name": "id",
          "type": "uuid",
          "primaryKey": true,
          "notNull": true,
          "default": "gen_random_uuid()"
        },
        "user_id": {
          "name": "user_id",
          "type": "text",
          "primaryKey": false,
          "notNull": true
        },
        "person_id": {
          "name": "person_id",
          "type": "uuid",
          "primaryKey": false,
          "notNull": false
        },
        "date_location": {
          "name": "date_location",
          "type": "text",
          "primaryKey": false,
          "notNull": false
        },
        "person_description": {
          "name": "person_description",
          "type": "text",
          "primaryKey": false,
          "notNull": false
        },
        "emergency_contacts": {
          "name": "emergency_contacts",
          "type": "text[]",
          "primaryKey": false,
          "notNull": false
        },
        "created_at": {
          "name": "created_at",
          "type": "timestamp with time zone",
          "primaryKey": false,
          "notNull": true,
          "default": "now()"
        }
      },
      "indexes": {},
      "foreignKeys": {
        "safety_checkins_user_id_user_id_fk": {
          "name": "safety_checkins_user_id_user_id_fk",
          "tableFrom": "safety_checkins",
          "tableTo": "user",
          "columnsFrom": [
            "user_id"
          ],
          "columnsTo": [
            "id"
          ],
          "onDelete": "cascade",
          "onUpdate": "no action"
        },
        "safety_checkins_person_id_persons_id_fk": {
          "name": "safety_checkins_person_id_persons_id_fk",
          "tableFrom": "safety_checkins",
          "tableTo": "persons",
          "columnsFrom": [
            "person_id"
          ],
          "columnsTo": [
            "id"
          ],
          "onDelete": "set null",
          "onUpdate": "no action"
        }
      },
      "compositePrimaryKeys": {},
      "uniqueConstraints": {},
      "policies": {},
      "checkConstraints": {},
      "isRLSEnabled": false
    },
    "public.share_tokens": {
      "name": "share_tokens",
      "schema": "",
      "columns": {
        "id": {
          "name": "id",
          "type": "uuid",
          "primaryKey": true,
          "notNull": true,
          "default": "gen_random_uuid()"
        },
        "user_id": {
          "name": "user_id",
          "type": "text",
          "primaryKey": false,
          "notNull": true
        },
        "token": {
          "name": "token",
          "type": "text",
          "primaryKey": false,
          "notNull": true
        },
        "expires_at": {
          "name": "expires_at",
          "type": "timestamp with time zone",
          "primaryKey": false,
          "notNull": true
        },
        "used": {
          "name": "used",
          "type": "boolean",
          "primaryKey": false,
          "notNull": true,
          "default": false
        },
        "created_at": {
          "name": "created_at",
          "type": "timestamp with time zone",
          "primaryKey": false,
          "notNull": true,
          "default": "now()"
        }
      },
      "indexes": {},
      "foreignKeys": {
        "share_tokens_user_id_user_id_fk": {
          "name": "share_tokens_user_id_user_id_fk",
          "tableFrom": "share_tokens",
          "tableTo": "user",
          "columnsFrom": [
            "user_id"
          ],
          "columnsTo": [
            "id"
          ],
          "onDelete": "cascade",
          "onUpdate": "no action"
        }
      },
      "compositePrimaryKeys": {},
      "uniqueConstraints": {
        "share_tokens_token_unique": {
          "name": "share_tokens_token_unique",
          "nullsNotDistinct": false,
          "columns": [
            "token"
          ]
        }
      },
      "policies": {},
      "checkConstraints": {},
      "isRLSEnabled": false
    },
    "public.user_preferences": {
      "name": "user_preferences",
      "schema": "",
      "columns": {
        "id": {
          "name": "id",
          "type": "uuid",
          "primaryKey": true,
          "notNull": true,
          "default": "gen_random_uuid()"
        },
        "user_id": {
          "name": "user_id",
          "type": "text",
          "primaryKey": false,
          "notNull": true
        },
        "notifications_enabled": {
          "name": "notifications_enabled",
          "type": "boolean",
          "primaryKey": false,
          "notNull": true,
          "default": true
        },
        "dark_mode_enabled": {
          "name": "dark_mode_enabled",
          "type": "boolean",
          "primaryKey": false,
          "notNull": true,
          "default": false
        },
        "created_at": {
          "name": "created_at",
          "type": "timestamp with time zone",
          "primaryKey": false,
          "notNull": true,
          "default": "now()"
        },
        "updated_at": {
          "name": "updated_at",
          "type": "timestamp with time zone",
          "primaryKey": false,
          "notNull": true,
          "default": "now()"
        }
      },
      "indexes": {},
      "foreignKeys": {
        "user_preferences_user_id_user_id_fk": {
          "name": "user_preferences_user_id_user_id_fk",
          "tableFrom": "user_preferences",
          "tableTo": "user",
          "columnsFrom": [
            "user_id"
          ],
          "columnsTo": [
            "id"
          ],
          "onDelete": "cascade",
          "onUpdate": "no action"
        }
      },
      "compositePrimaryKeys": {},
      "uniqueConstraints": {
        "user_preferences_user_id_unique": {
          "name": "user_preferences_user_id_unique",
          "nullsNotDistinct": false,
          "columns": [
            "user_id"
          ]
        }
      },
      "policies": {},
      "checkConstraints": {},
      "isRLSEnabled": false
    },
    "public.user_profiles": {
      "name": "user_profiles",
      "schema": "",
      "columns": {
        "id": {
          "name": "id",
          "type": "uuid",
          "primaryKey": true,
          "notNull": true,
          "default": "gen_random_uuid()"
        },
        "user_id": {
          "name": "user_id",
          "type": "text",
          "primaryKey": false,
          "notNull": true
        },
        "display_name": {
          "name": "display_name",
          "type": "text",
          "primaryKey": false,
          "notNull": false
        },
        "photo_url": {
          "name": "photo_url",
          "type": "text",
          "primaryKey": false,
          "notNull": false
        },
        "age": {
          "name": "age",
          "type": "integer",
          "primaryKey": false,
          "notNull": false
        },
        "birthday": {
          "name": "birthday",
          "type": "text",
          "primaryKey": false,
          "notNull": false
        },
        "zodiac": {
          "name": "zodiac",
          "type": "text",
          "primaryKey": false,
          "notNull": false
        },
        "location": {
          "name": "location",
          "type": "text",
          "primaryKey": false,
          "notNull": false
        },
        "occupation": {
          "name": "occupation",
          "type": "text",
          "primaryKey": false,
          "notNull": false
        },
        "bio": {
          "name": "bio",
          "type": "text",
          "primaryKey": false,
          "notNull": false
        },
        "favorite_foods": {
          "name": "favorite_foods",
          "type": "text[]",
          "primaryKey": false,
          "notNull": false
        },
        "hobbies": {
          "name": "hobbies",
          "type": "text[]",
          "primaryKey": false,
          "notNull": false
        },
        "what_i_bring": {
          "name": "what_i_bring",
          "type": "text[]",
          "primaryKey": false,
          "notNull": false
        },
        "things_to_work_on": {
          "name": "things_to_work_on",
          "type": "text[]",
          "primaryKey": false,
          "notNull": false
        },
        "green_flags": {
          "name": "green_flags",
          "type": "text[]",
          "primaryKey": false,
          "notNull": false
        },
        "red_flags": {
          "name": "red_flags",
          "type": "text[]",
          "primaryKey": false,
          "notNull": false
        },
        "attractiveness_self": {
          "name": "attractiveness_self",
          "type": "integer",
          "primaryKey": false,
          "notNull": false
        },
        "communication_self": {
          "name": "communication_self",
          "type": "integer",
          "primaryKey": false,
          "notNull": false
        },
        "instagram": {
          "name": "instagram",
          "type": "text",
          "primaryKey": false,
          "notNull": false
        },
        "tiktok": {
          "name": "tiktok",
          "type": "text",
          "primaryKey": false,
          "notNull": false
        },
        "twitter_x": {
          "name": "twitter_x",
          "type": "text",
          "primaryKey": false,
          "notNull": false
        },
        "phone_number": {
          "name": "phone_number",
          "type": "text",
          "primaryKey": false,
          "notNull": false
        },
        "created_at": {
          "name": "created_at",
          "type": "timestamp with time zone",
          "primaryKey": false,
          "notNull": true,
          "default": "now()"
        },
        "updated_at": {
          "name": "updated_at",
          "type": "timestamp with time zone",
          "primaryKey": false,
          "notNull": true,
          "default": "now()"
        }
      },
      "indexes": {},
      "foreignKeys": {
        "user_profiles_user_id_user_id_fk": {
          "name": "user_profiles_user_id_user_id_fk",
          "tableFrom": "user_profiles",
          "tableTo": "user",
          "columnsFrom": [
            "user_id"
          ],
          "columnsTo": [
            "id"
          ],
          "onDelete": "cascade",
          "onUpdate": "no action"
        }
      },
      "compositePrimaryKeys": {},
      "uniqueConstraints": {
        "user_profiles_user_id_unique": {
          "name": "user_profiles_user_id_unique",
          "nullsNotDistinct": false,
          "columns": [
            "user_id"
          ]
        }
      },
      "policies": {},
      "checkConstraints": {},
      "isRLSEnabled": false
    }
  },
  "enums": {
    "public.chat_role": {
      "name": "chat_role",
      "schema": "public",
      "values": [
        "user",
        "assistant"
      ]
    },
    "public.connection_type": {
      "name": "connection_type",
      "schema": "public",
      "values": [
        "friend",
        "casual",
        "booty_call",
        "foodie_call",
        "figuring_it_out",
        "serious",
        "other"
      ]
    },
    "public.date_status": {
      "name": "date_status",
      "schema": "public",
      "values": [
        "planned",
        "confirmed",
        "completed",
        "cancelled"
      ]
    },
    "public.interaction_type": {
      "name": "interaction_type",
      "schema": "public",
      "values": [
        "date",
        "text",
        "call",
        "other"
      ]
    },
    "public.zodiac": {
      "name": "zodiac",
      "schema": "public",
      "values": [
        "aries",
        "taurus",
        "gemini",
        "cancer",
        "leo",
        "virgo",
        "libra",
        "scorpio",
        "sagittarius",
        "capricorn",
        "aquarius",
        "pisces"
      ]
    }
  },
  "schemas": {},
  "sequences": {},
  "roles": {},
  "policies": {},
  "views": {},
  "_meta": {
    "columns": {},
    "schemas": {},
    "tables": {}
  }
}